odoo10_addon_intrastat_product_generic-10.0.1.0.0.99.dev3-py2.7-nspkg.pth
odoo/addons/intrastat_product_generic/README.rst
odoo/addons/intrastat_product_generic/__init__.py
odoo/addons/intrastat_product_generic/__manifest__.py
odoo/addons/intrastat_product_generic/i18n/intrastat_product_generic.pot
odoo/addons/intrastat_product_generic/security/intrastat_security.xml
odoo/addons/intrastat_product_generic/static/description/icon.png
odoo/addons/intrastat_product_generic/views/intrastat_product.xml
odoo10_addon_intrastat_product_generic-10.0.1.0.0.99.dev3.dist-info/METADATA
odoo10_addon_intrastat_product_generic-10.0.1.0.0.99.dev3.dist-info/RECORD
odoo10_addon_intrastat_product_generic-10.0.1.0.0.99.dev3.dist-info/WHEEL
odoo10_addon_intrastat_product_generic-10.0.1.0.0.99.dev3.dist-info/namespace_packages.txt
odoo10_addon_intrastat_product_generic-10.0.1.0.0.99.dev3.dist-info/top_level.txt
