Metadata-Version: 2.1
Name: odoo10-addon-intrastat-product-generic
Version: 10.0.1.0.0.99.dev3
Summary: Generic Intrastat Product Declaration
Home-page: https://github.com/OCA/intrastat
Author: Noviat,Odoo Community Association (OCA)
Author-email: support@odoo-community.org
License: AGPL-3
Platform: UNKNOWN
Classifier: Programming Language :: Python
Classifier: Framework :: Odoo
Classifier: License :: OSI Approved :: GNU Affero General Public License v3
Requires-Python: ~=2.7
Requires-Dist: odoo10-addon-intrastat-product
Requires-Dist: odoo (<10.1dev,>=10.0)
